MANIFEST.in
README.md
setup.py
pwr/InputTextDialog.py
pwr/InputTextDialogUi.py
pwr/__init__.py
pwr/wysiwyg.py
pwr.egg-info/PKG-INFO
pwr.egg-info/SOURCES.txt
pwr.egg-info/dependency_links.txt
pwr.egg-info/entry_points.txt
pwr.egg-info/requires.txt
pwr.egg-info/top_level.txt
pwr/config/pwr.conf