Metadata-Version: 1.0
Name: pwr
Version: 2.6
Summary: This program helps you write html pages like documents in word processors
Home-page: https://github.com/Friz-zy/WYSIWYG
Author: Filipp Frizzy
Author-email: filipp.s.frizzy@gmail.com
License: BSD3
Keywords: python wysiwyg html documents qt webkit
Platform: UNKNOWN
